Metadata-Version: 1.0
Name: heberto-test
Version: 0.1
Summary: Test for Udacity with distributions
Home-page: UNKNOWN
Author: UNKNOWN
Author-email: UNKNOWN
License: UNKNOWN
Platform: UNKNOWN
